<?xml version="1.0" encoding="UTF-8"?>
<resourceManager>
	<models>
		<model id="1">
			<path>Resources/Models/croco.nfg</path>
		</model>
		<model id="5">
			<path>Resources/Models/bila.nfg</path>
		</model>
		<model id="11">
			<path>Resources/Models/SkyBox.nfg</path>
		</model>
		<!-- si aici se adauga toate modelele -->
	</models>
	<shaders>
		<shader id="1">
			<vs>Resources/Shaders/vertexShader.vs</vs>
			<fs>Resources/Shaders/fragmentShader.fs</fs>
		</shader>
		<shader id="3">
			<vs>Resources/Shaders/terrainShader.vs</vs>
			<fs>Resources/Shaders/terrainShader.fs</fs>
		</shader>
		<shader id="13">
			<vs>Resources/Shaders/skyboxShader.vs</vs>
			<fs>Resources/Shaders/skyboxShader.fs</fs>
		</shader>
		<!-- si aici se adauga toate shaderele -->
	</shaders>
	<textures>
		<texture id="8" type="2d">
			<path>Resources/Textures/croco.tga</path>			
			<min_filter>LINEAR</min_filter>
			<mag_filter>LINEAR</mag_filter>
			<wrap_s>CLAMP_TO_EDGE</wrap_s>
			<wrap_t>CLAMP_TO_EDGE</wrap_t>
		</texture>
		<texture id="5" type="2d">
			<path>Resources/Textures/bus.tga</path>
			<min_filter>LINEAR</min_filter>
			<mag_filter>LINEAR</mag_filter>
			<wrap_s>CLAMP_TO_EDGE</wrap_s>
			<wrap_t>CLAMP_TO_EDGE</wrap_t>
		</texture>
		<texture id="6" type="2d">
			<path>Resources/Textures/Grass.tga</path>
			<min_filter>LINEAR</min_filter>
			<mag_filter>LINEAR</mag_filter>
			<wrap_s>REPEAT</wrap_s>
			<wrap_t>REPEAT</wrap_t>
		</texture>
		<texture id="7" type="2d">
			<path>Resources/Textures/Dirt.tga</path>
			<min_filter>LINEAR</min_filter>
			<mag_filter>LINEAR</mag_filter>
			<wrap_s>REPEAT</wrap_s>
			<wrap_t>REPEAT</wrap_t>
		</texture>
		<texture id="9" type="2d">
			<path>Resources/Textures/Rock.tga</path>
			<min_filter>LINEAR</min_filter>
			<mag_filter>LINEAR</mag_filter>
			<wrap_s>REPEAT</wrap_s>
			<wrap_t>REPEAT</wrap_t>
		</texture>
		<texture id="10" type="2d">
			<path>Resources/Textures/Terrain_blend_map.tga</path>
			<min_filter>LINEAR</min_filter>
			<mag_filter>LINEAR</mag_filter>
			<wrap_s>REPEAT</wrap_s>
			<wrap_t>REPEAT</wrap_t>
		</texture>
		<texture id="12" type="3d">
			<path>Resources/Textures/envMap.tga</path>
			<min_filter>LINEAR</min_filter>
			<mag_filter>LINEAR</mag_filter>
			<wrap_s>CLAMP_TO_EDGE</wrap_s>
			<wrap_t>CLAMP_TO_EDGE</wrap_t>
		</texture>
		<!-- si aici se adauga toate texturile -->
	</textures>	
</resourceManager>